[
  {
    "id": "2013-2847",
    "event_id": "2847",
    "event_year": "2013",
    "title": "SD State 40K Time Trial Championship",
    "category": "E",
    "address": {
      "street": "",
      "city": "Crooks",
      "state": "SD",
      "zip": "57020"
    },
    "lat": null,
    "lon": null,
    "organizer": "287925",
    "email": "canderson@fca.org",
    "contact": "0",
    "date_start": "2013-07-27",
    "date_end": "2013-07-27",
    "setup_date_start": "",
    "setup_date_end": "",
    "training_date_start": "",
    "training_date_end": "",
    "teardown_date_start": "",
    "teardown_date_end": "",
    "registration_start": "-0001-11-30",
    "registration_late": "-0001-11-30",
    "registration_end": "-0001-11-30",
    "usac_registration": "N",
    "ncca": "",
    "ncca_conf": "",
    "web_page": "fcaendurance.com/sdstatett",
    "reg_url": "www.allsportcentral.com/EventInfo.cfm?EventID=53600",
    "flyer_url": "FL_2013-2847.pdf",
    "status": "4",
    "competitive": "Y",
    "kidsfunride": "N",
    "nonconsecutive": "",
    "registration_groupid": "0",
    "registration_hold": "N",
    "registration_notify": "N",
    "event_days": "1",
    "description": "",
    "course": "",
    "registration": "",
    "notes": "",
    "directions": "",
    "hide": "n",
    "_discipline": "ROAD"
  },
  {
    "id": "2013-761",
    "event_id": "761",
    "event_year": "2013",
    "title": "Canton Cycling Classic - Flyover Race #5 & SD Stat",
    "category": "B",
    "address": {
      "street": "",
      "city": "Canton",
      "state": "SD",
      "zip": "57013"
    },
    "lat": null,
    "lon": null,
    "organizer": "227206",
    "email": "",
    "contact": "227206",
    "date_start": "2013-08-24",
    "date_end": "2013-08-25",
    "setup_date_start": "",
    "setup_date_end": "",
    "training_date_start": "",
    "training_date_end": "",
    "teardown_date_start": "",
    "teardown_date_end": "",
    "registration_start": "2013-02-11",
    "registration_late": "-0001-11-30",
    "registration_end": "2013-08-22",
    "usac_registration": "Y",
    "ncca": "",
    "ncca_conf": "",
    "web_page": "www.cantoncyclingclassic.org",
    "reg_url": "",
    "flyer_url": "FL_2013-761.pdf",
    "status": "4",
    "competitive": "Y",
    "kidsfunride": "N",
    "nonconsecutive": "",
    "registration_groupid": "0",
    "registration_hold": "N",
    "registration_notify": "N",
    "event_days": "2",
    "description": "",
    "course": "",
    "registration": "",
    "notes": "",
    "directions": "",
    "hide": "n",
    "_discipline": "ROAD"
  },
  {
    "id": "2013-3497",
    "event_id": "3497",
    "event_year": "2013",
    "title": "The Elmwood Forest Cross",
    "category": "D",
    "address": {
      "street": "2601 Russell St.",
      "city": "Sioux Falls",
      "state": "SD",
      "zip": "57104"
    },
    "lat": 43.5630726,
    "lon": -96.7640783,
    "organizer": "389545",
    "email": "owen@spoke-n-sport.com",
    "contact": "389545",
    "date_start": "2013-10-13",
    "date_end": "2013-10-13",
    "setup_date_start": "",
    "setup_date_end": "",
    "training_date_start": "",
    "training_date_end": "",
    "teardown_date_start": "",
    "teardown_date_end": "",
    "registration_start": "2013-09-04",
    "registration_late": "2013-10-11",
    "registration_end": "2013-10-12",
    "usac_registration": "Y",
    "ncca": "",
    "ncca_conf": "",
    "web_page": "spoke-n-sport.com/goto/cross",
    "reg_url": "",
    "flyer_url": "",
    "status": "4",
    "competitive": "Y",
    "kidsfunride": "N",
    "nonconsecutive": "",
    "registration_groupid": "0",
    "registration_hold": "N",
    "registration_notify": "Y",
    "event_days": "1",
    "description":
      "Queen City Cycling and a band of merry cross racers in Sioux Falls on Oct. 13. Men&#39;s and women&#39;s races.",
    "course":
      "A challenging and technical Cross circuit carved from the Elmwood grove of giant cottonwoods and oaks along the Big Sioux River.",
    "registration":
      "Entry fee is $25. Online registration available until 11 p.m. Oct. 12. Race day registration available at site. Riders must show valid USA Cycling license. One day licenses will be available day of race for $10. Registration opens at 11 a.m. and closes 30 minutes prior to each event. Entry fees: as stated. Include $3 USCF insurance. No Refunds/ No free lap Online registration http://www.usacycling.org",
    "notes":
      "Lodging available on location at Sleep Inn Airport &#x28;sleepinn.com&#x29;. Also recommended lodging within short distance at Sheraton Sioux Falls & Convention Center &#x28;starwoodhotels.com&#x29;.\r\nFor more information go to www.spoke-n-sport.com or call 605-275-2453",
    "directions":
      "Elmwood Park is located at the intersection of Russell Street and Kiwanis Avenue in Sioux Falls. From Interstate 29, take the Russell Street exit and go east approximately one mile to Kiwanis Ave. Entrance to the park is about a quarter mile south on Kiwanis Avenue. ",
    "hide": "n",
    "_discipline": "CX"
  }
]
