[
  {
    "id": "2014-1430",
    "event_id": "1430",
    "event_year": "2014",
    "title": "SMCC Spring Crit Series",
    "category": "E",
    "address": {
      "street": "",
      "city": "Scarborough",
      "state": "ME",
      "zip": "04074"
    },
    "lat": null,
    "lon": null,
    "organizer": "224607",
    "email": "",
    "contact": "0",
    "date_start": "2014-04-06",
    "date_end": "2014-05-18",
    "setup_date_start": "",
    "setup_date_end": "",
    "training_date_start": "",
    "training_date_end": "",
    "teardown_date_start": "",
    "teardown_date_end": "",
    "registration_start": "-0001-11-30",
    "registration_late": "-0001-11-30",
    "registration_end": "-0001-11-30",
    "usac_registration": "N",
    "ncca": "",
    "ncca_conf": "",
    "web_page": "",
    "reg_url": "",
    "flyer_url": "FL_2014-1430.pdf",
    "status": "4",
    "competitive": "S",
    "kidsfunride": "N",
    "nonconsecutive": "",
    "registration_groupid": "0",
    "registration_hold": "N",
    "registration_notify": "N",
    "event_days": "7",
    "description": "",
    "course": "",
    "registration": "",
    "notes": "",
    "directions": "",
    "hide": "n",
    "_discipline": "ROAD"
  },
  {
    "id": "2014-1706",
    "event_id": "1706",
    "event_year": "2014",
    "title": "CycleMania Time Trial",
    "category": "E",
    "address": {
      "street": "",
      "city": "Cape Elizabeth",
      "state": "ME",
      "zip": "04107"
    },
    "lat": null,
    "lon": null,
    "organizer": "4858",
    "email": "dbrink@maine.rr.com",
    "contact": "4858",
    "date_start": "2014-05-18",
    "date_end": "2014-05-18",
    "setup_date_start": "",
    "setup_date_end": "",
    "training_date_start": "",
    "training_date_end": "",
    "teardown_date_start": "",
    "teardown_date_end": "",
    "registration_start": "-0001-11-30",
    "registration_late": "-0001-11-30",
    "registration_end": "-0001-11-30",
    "usac_registration": "N",
    "ncca": "",
    "ncca_conf": "",
    "web_page": "www.portlandvelo.com",
    "reg_url": "www.bikereg.com",
    "flyer_url": "FL_2014-1706.pdf",
    "status": "4",
    "competitive": "Y",
    "kidsfunride": "N",
    "nonconsecutive": "",
    "registration_groupid": "0",
    "registration_hold": "N",
    "registration_notify": "N",
    "event_days": "1",
    "description": "",
    "course": "",
    "registration": "",
    "notes": "",
    "directions": "",
    "hide": "n",
    "_discipline": "ROAD"
  },
  {
    "id": "2014-1708",
    "event_id": "1708",
    "event_year": "2014",
    "title": "Yarmouth Clam Festival Bike Race",
    "category": "D",
    "address": {
      "street": "",
      "city": "Yarmouth",
      "state": "ME",
      "zip": "04101"
    },
    "lat": 43.6629964,
    "lon": -70.2568775,
    "organizer": "4858",
    "email": "dbrink@maine.rr.com",
    "contact": "4858",
    "date_start": "2014-07-20",
    "date_end": "2014-07-20",
    "setup_date_start": "",
    "setup_date_end": "",
    "training_date_start": "",
    "training_date_end": "",
    "teardown_date_start": "",
    "teardown_date_end": "",
    "registration_start": "-0001-11-30",
    "registration_late": "-0001-11-30",
    "registration_end": "-0001-11-30",
    "usac_registration": "N",
    "ncca": "",
    "ncca_conf": "",
    "web_page": "www.portlandvelo.com",
    "reg_url": "www.bikereg.com",
    "flyer_url": "FL_2014-1708.docx",
    "status": "4",
    "competitive": "Y",
    "kidsfunride": "N",
    "nonconsecutive": "",
    "registration_groupid": "0",
    "registration_hold": "N",
    "registration_notify": "N",
    "event_days": "1",
    "description": "",
    "course": "",
    "registration": "",
    "notes": "",
    "directions": "",
    "hide": "n",
    "_discipline": "ROAD"
  },
  {
    "id": "2014-1874",
    "event_id": "1874",
    "event_year": "2014",
    "title": "Balloon Festival Crit",
    "category": "D",
    "address": {
      "street": "97 Lisbon St",
      "city": "Lewiston",
      "state": "ME",
      "zip": "04240"
    },
    "lat": null,
    "lon": null,
    "organizer": "66046",
    "email": "John@rainbowbike.com",
    "contact": "0",
    "date_start": "2014-08-17",
    "date_end": "2014-08-17",
    "setup_date_start": "",
    "setup_date_end": "",
    "training_date_start": "",
    "training_date_end": "",
    "teardown_date_start": "",
    "teardown_date_end": "",
    "registration_start": "1969-12-31",
    "registration_late": "-0001-11-30",
    "registration_end": "1969-12-31",
    "usac_registration": "N",
    "ncca": "",
    "ncca_conf": "",
    "web_page": "",
    "reg_url": "Bikereg.com",
    "flyer_url": "FL_2014-1874.pdf",
    "status": "4",
    "competitive": "Y",
    "kidsfunride": "Y",
    "nonconsecutive": "",
    "registration_groupid": "0",
    "registration_hold": "N",
    "registration_notify": "",
    "event_days": "1",
    "description": "Criterium in downtown Lewiston",
    "course": "1 mile , technical 6 turn loop in an urban area.",
    "registration":
      "Registration opens at 8:30am. Pre registration is recommended. Online registration is available on Bikereg at www.bikereg.com. Bikereg applies a standard service fee to entries. There will be a $10 late fee charged to &#x22;day of&#x22; entries. There will be NO REFUNDS. One day licenses are available for $15.00 on the day of the race. USAC License is required in all but Kid&#39;s races. BY mail please send completed 2014 USAC entry/ Release form to Rainbow Bike, 97 Lisbon st., Lewiston, ME 04240",
    "notes": "USAC rules will apply, Helmets required, no tank tops allowed ",
    "directions":
      "From North or South take Lewiston Exit 80 off Interstate RT 95. Take left onto Alfred Plourde Parkway, go .2 miles and look for RT 196/ Lisbon st. Lewiston &#x28;2nd right ramp&#x29;. Follow to 97 Lisbon St &#x28;Rainbow Bike registration area&#x29;",
    "hide": "n",
    "_discipline": "ROAD"
  },
  {
    "id": "2014-2913",
    "event_id": "2913",
    "event_year": "2014",
    "title": "Downeast Cyclocross",
    "category": "D",
    "address": {
      "street": "Pineland Farms, New Gloucester, Maine",
      "city": "New Gloucester",
      "state": "ME",
      "zip": "04260"
    },
    "lat": null,
    "lon": null,
    "organizer": "66046",
    "email": "",
    "contact": "66046",
    "date_start": "2014-10-18",
    "date_end": "2014-10-18",
    "setup_date_start": "",
    "setup_date_end": "",
    "training_date_start": "",
    "training_date_end": "",
    "teardown_date_start": "",
    "teardown_date_end": "",
    "registration_start": "1969-12-31",
    "registration_late": "-0001-11-30",
    "registration_end": "1969-12-31",
    "usac_registration": "N",
    "ncca": "",
    "ncca_conf": "",
    "web_page": "",
    "reg_url": "Bikereg",
    "flyer_url": "FL_2014-2913.png",
    "status": "4",
    "competitive": "Y",
    "kidsfunride": "Y",
    "nonconsecutive": "",
    "registration_groupid": "0",
    "registration_hold": "N",
    "registration_notify": "",
    "event_days": "1",
    "description":
      "Cyclocross racing at Pineland Farms, New Gloucester, Maine during peak foliage season. Spectacular scenery, great venue, challenging course. Kids races and even single speed categories",
    "course":
      "This years course returns to the upper part of the Pinelands Farm campus. Mix of open field and woods trails that Pineland is famous for. ",
    "registration":
      "Registration: Entry fee for all races is $30. Entries must be received by Tuesday Oct. 14th, 2014 at 5:00 PM ET, or add $5.00 late fee. Entry fee includes all applicable USA Cycling Insurance surcharge. No refunds on day of event. One Day licenses will be available for purchase. Day-of registration opens at 8:30am. Riders must  register at least 30 minutes prior to the start of their event.\r\n\r\nNote: Riders can race in additional races for $15. Start positions determined by rider rankings at crossresults.com.\r\n\r\nOn-line registration only at www.bikereg.com.On-line service fee applied based on bikereg.com standard service rates",
    "notes":
      "Check out the event venue at www.pinelandfarms.org there is plenty there to keep the whole family interested for the weekend.\r\n\r\nALSO- Dogs are not allowed at Pineland farms, you won&#39;t be allowed to bring your dog out of the car even if on a leash, sorry!",
    "directions":
      "Directions- Take the Maine Turnpike to Exit 63 in Gray, Maine. Bear to the right after the toll booth toward the center of Gray Village. Stay in the right lane. At the first intersection, go straight through the light onto rt 115 and continue on rt 115&#x28;east&#x29;  then turn left onto Mill St.. Continue on Mill till you reach Rt 231/ Intervale Rd. Turn left onto rt 231/ Intervale road then left onto Morse rd. and enter the Campus on your right.",
    "hide": "n",
    "_discipline": "CX"
  },
  {
    "id": "2014-2909",
    "event_id": "2909",
    "event_year": "2014",
    "title": "Casco Bay Cyclocross",
    "category": "E",
    "address": {
      "street": "",
      "city": "Portland",
      "state": "ME",
      "zip": "04101"
    },
    "lat": null,
    "lon": null,
    "organizer": "303505",
    "email": "nicole@strategic-racing.com",
    "contact": "0",
    "date_start": "2014-10-19",
    "date_end": "2014-10-19",
    "setup_date_start": "2014-10-18",
    "setup_date_end": "2014-10-18",
    "training_date_start": "",
    "training_date_end": "",
    "teardown_date_start": "2014-10-20",
    "teardown_date_end": "2014-10-20",
    "registration_start": "1969-12-31",
    "registration_late": "-0001-11-30",
    "registration_end": "1969-12-31",
    "usac_registration": "N",
    "ncca": "",
    "ncca_conf": "",
    "web_page": "www.cascobaycross.com",
    "reg_url": "www.bikereg.com/cascobaycross",
    "flyer_url": "",
    "status": "4",
    "competitive": "Y",
    "kidsfunride": "N",
    "nonconsecutive": "",
    "registration_groupid": "0",
    "registration_hold": "N",
    "registration_notify": "",
    "event_days": "1",
    "description":
      "Working closely with lead sponsor Bikeman.com, Strategic Racing and Training presents an annual grass roots cyclocross race on the beautiful Eastern Promenade in Portland, Maine. The course and spectator viewing areas feature stunning views of Casco Bay. The venue offers plenty of parking, a playground for the kids, access to walking paths and picnic areas. Local food trucks will cater to racers and spectators throughout the day. Event proceeds are annually donated to the Eastern Promenade associate non-profit: Friends of the Eastern Promenade.",
    "course":
      "The Casco Bay Cyclocross course will take place on the Eastern Promenade overlooking Casco Bay. The course weaves throughout the Eastern Prom trails utilizing man made and natural obstacles, steep climbs, and unique downhills. It includes a mix of grassy fields, single and double track, and a paved road section where the course begins and ends. There will be two sets of barriers, one short, steep climb, and one pit. The course is skillfully designed and set up by Bikeman.com.",
    "registration": "https://www.bikereg.com/cascobaycross",
    "notes": "",
    "directions":
      "By Car\r\nFrom Boston: 95 North to I-295 North, exit 7 &#x28;Franklin Arterial&#x29; Take right off exit to go Franklin St. Turn left on Fox St. Turn left onto Washington Ave. Take the first right on Walnut St. The race is at the bottom of Walnut St. on the Eastern Promenade.\r\n\r\nFrom Points North: Take 95 South to I-295 South – follow the above in town directions.\r\n\r\nFrom Points West: Take Route 302 East to I-295 – follow the above in town directions.\r\n\r\nBy Bike\r\nThe Eastern Promenade is located at the intersection of Congress Street and Eastern Promenade. Follow the road or or the Eastern Promenade Trail to the venue on top of the hill.\r\n\r\nBy Train\r\nThe Amtrak Downeaster runs from Boston to Portland.",
    "hide": "n",
    "_discipline": "CX"
  }
]
